imread-0.7.6.dist-info/top_level.txt
imread-0.7.6.dist-info/RECORD
imread-0.7.6.dist-info/COPYING.MIT
imread-0.7.6.dist-info/METADATA
imread-0.7.6.dist-info/WHEEL
imread-0.7.6.dist-info/AUTHORS
imread/imread_version.py
imread/ijrois.py
imread/__init__.py
imread/imread.py
imread/_imread.cpython-38-x86_64-linux-gnu.so
imread/special.py
imread/tests/test_error.py
imread/tests/test_png.py
imread/tests/test_bmp.py
imread/tests/test_tiff.py
imread/tests/test_bad.py
imread/tests/test_jpeg.py
imread/tests/__init__.py
imread/tests/test_imread_from_blob.py
imread/tests/test_webp.py
imread/tests/test_imsave.py
imread/tests/test_xcf.py
imread/tests/test_rois.py
imread/tests/test_formats.py
imread/tests/test_imread.py
imread/tests/data/mono.tif
imread/tests/data/bit1.png
imread/tests/data/error.jpg
imread/tests/data/diag.xcf
imread/tests/data/error.webp
imread/tests/data/arange512_16bit.png
imread/tests/data/star1.bmp
imread/tests/data/py-installer-indexed.bmp
imread/tests/data/error.tif
imread/tests/data/rgba.png
imread/tests/data/error.png
imread/tests/data/error.unknown
imread/tests/data/good
imread/tests/data/rois.zip
imread/tests/data/good.png
imread/tests/data/ghsystem_flame.jpg
imread/tests/data/paletted_rgba.png
imread/tests/data/stack.tiff
imread/tests/data/GOOD.PNG
imread/tests/data/0186-0099.roi
imread/tests/data/palette_zero.png
imread/tests/data/bad-files/LSM/02r/02r02.lsm
imread/tests/data/bad-files/LSM/02r/02r00.lsm
imread/tests/data/bad-files/LSM/02r/02r01.lsm
imread/tests/data/bad-files/LSM/00r/00r02.lsm
imread/tests/data/bad-files/LSM/00r/00r03.lsm
imread/tests/data/bad-files/LSM/00r/00r01.lsm
imread/tests/data/bad-files/LSM/00r/00r00.lsm
imread/tests/data/bad-files/LSM/03w/03w00.lsm
imread/tests/data/bad-files/LSM/03w/03w01.lsm
imread/tests/data/bad-files/LSM/03w/03w03.lsm
imread/tests/data/bad-files/LSM/03w/03w02.lsm
imread/tests/data/bad-files/LSM/01r/01r02.lsm
imread/tests/data/bad-files/LSM/01r/01r01.lsm
imread/tests/data/bad-files/LSM/01r/01r00.lsm
imread/tests/data/bad-files/TIFF/00r00.tiff
imread/tests/data/bad-files/BMP/00r/00r04.bmp
imread/tests/data/bad-files/BMP/00r/00r02.bmp
