Metadata-Version: 2.1
Name: imread
Version: 0.7.6
Summary: imread: Image reading library
Home-page: http://luispedro.org/software/imread
Author: Luis Pedro Coelho
Author-email: luis@luispedro.org
License: MIT
Platform: Any
Classifier: Development Status :: 5 - Production/Stable
Classifier: Intended Audience :: Developers
Classifier: Intended Audience :: Science/Research
Classifier: Topic :: Multimedia
Classifier: Topic :: Scientific/Engineering :: Image Recognition
Classifier: Topic :: Software Development :: Libraries
Classifier: Programming Language :: Python
Classifier: Programming Language :: Python :: 3
Classifier: Programming Language :: Python :: 3.3
Classifier: Programming Language :: Python :: 3.4
Classifier: Programming Language :: Python :: 3.5
Classifier: Programming Language :: Python :: 3.6
Classifier: Programming Language :: Python :: 3.7
Classifier: Programming Language :: Python :: 3.8
Classifier: Programming Language :: Python :: 3.9
Classifier: Programming Language :: Python :: 3.10
Classifier: Programming Language :: Python :: 3.11
Classifier: Programming Language :: C++
Classifier: License :: OSI Approved :: MIT License
License-File: COPYING.MIT
License-File: AUTHORS
Requires-Dist: numpy
